hawkins_rag/__init__.py
hawkins_rag/cli.py
hawkins_rag/config.py
hawkins_rag/core.py
hawkins_rag/utils.py
hawkins_rag/loaders/__init__.py
hawkins_rag/loaders/audio.py
hawkins_rag/loaders/base.py
hawkins_rag/loaders/beehive.py
hawkins_rag/loaders/confluence_loader.py
hawkins_rag/loaders/csv.py
hawkins_rag/loaders/directory.py
hawkins_rag/loaders/discord.py
hawkins_rag/loaders/discourse.py
hawkins_rag/loaders/docx.py
hawkins_rag/loaders/dropbox.py
hawkins_rag/loaders/excel.py
hawkins_rag/loaders/github.py
hawkins_rag/loaders/gmail.py
hawkins_rag/loaders/googledrive.py
hawkins_rag/loaders/jira_loader.py
hawkins_rag/loaders/json_loader.py
hawkins_rag/loaders/local_text_loader.py
hawkins_rag/loaders/mdx_loader.py
hawkins_rag/loaders/mysql_loader.py
hawkins_rag/loaders/notion.py
hawkins_rag/loaders/openapi_loader.py
hawkins_rag/loaders/pdf.py
hawkins_rag/loaders/postgresql_loader.py
hawkins_rag/loaders/qna_loader.py
hawkins_rag/loaders/registry.py
hawkins_rag/loaders/rss_loader.py
hawkins_rag/loaders/slack_loader.py
hawkins_rag/loaders/text_loader.py
hawkins_rag/loaders/unstructured_loader.py
hawkins_rag/loaders/webpage_loader.py
hawkins_rag/loaders/xml_loader.py
hawkins_rag/loaders/youtube_loader.py
hawkins_rag/utils/__init__.py
hawkins_rag/utils/base.py
hawkins_rag/utils/google_auth.py
hawkins_rag/utils/loader_registry.py
hawkins_rag-0.1.0.dist-info/METADATA
hawkins_rag-0.1.0.dist-info/WHEEL
hawkins_rag-0.1.0.dist-info/licenses/LICENSE
hawkins_rag-0.1.0.dist-info/RECORD
